{
  "crypto15m_eval": {
    "accuracy_direction": 0.3333,
    "total_signals": 6,
    "correct_signals": 2,
    "windows_observed": 6,
    "avg_edge": 0.3134,
    "results": [
      {
        "ticker": "KXBTC15M-26JUN180145-45",
        "symbol": "BTC",
        "ts": "2026-06-18T05:45:31.002046Z",
        "n_points": 77,
        "final_price": 0.92,
        "had_signal": true,
        "outcome": 1,
        "correct": false,
        "edge": -0.38613861386138615
      },
      {
        "ticker": "KXBNB15M-26JUN180145-45",
        "symbol": "BNB",
        "ts": "2026-06-18T05:45:31.002046Z",
        "n_points": 32,
        "final_price": 0.5524,
        "had_signal": true,
        "outcome": -1,
        "correct": false,
        "edge": 0.0
      },
      {
        "ticker": "KXHYPE15M-26JUN180145-45",
        "symbol": "HYPE",
        "ts": "2026-06-18T05:45:31.002046Z",
        "n_points": 33,
        "final_price": 0.0099,
        "had_signal": true,
        "outcome": 0,
        "correct": false,
        "edge": 0.40594059405940597
      },
      {
        "ticker": "KXBTC15M-26JUN180145-45",
        "symbol": "BTC",
        "ts": "2026-06-18T05:45:31.001507Z",
        "n_points": 77,
        "final_price": 0.92,
        "had_signal": true,
        "outcome": 1,
        "correct": false,
        "edge": -0.38613861386138615
      },
      {
        "ticker": "KXSOL15M-26JUN180145-45",
        "symbol": "SOL",
        "ts": "2026-06-18T05:45:31.001507Z",
        "n_points": 49,
        "final_price": 1.0,
        "had_signal": true,
        "outcome": 1,
        "correct": true,
        "edge": 0.4095238095238095
      },
      {
        "ticker": "KXSOL15M-26JUN180145-45",
        "symbol": "SOL",
        "ts": "2026-06-18T05:45:42.477669Z",
        "n_points": 37,
        "final_price": 1.0,
        "had_signal": true,
        "outcome": 1,
        "correct": true,
        "edge": 0.2924528301886793
      }
    ]
  }
}